aliyunsdkft/__init__.py
aliyunsdkft/endpoint.py
aliyunsdkft/request/__init__.py
aliyunsdkft/request/v20180713/BatchAuditTest01Request.py
aliyunsdkft/request/v20180713/FTApiAliasApiRequest.py
aliyunsdkft/request/v20180713/FtDynamicAddressDubboRequest.py
aliyunsdkft/request/v20180713/FtDynamicAddressHsfRequest.py
aliyunsdkft/request/v20180713/FtDynamicAddressHttpVpcRequest.py
aliyunsdkft/request/v20180713/FtEagleEyeRequest.py
aliyunsdkft/request/v20180713/FtFlowSpecialRequest.py
aliyunsdkft/request/v20180713/FtGatedLaunchPolicy4Request.py
aliyunsdkft/request/v20180713/FtIpFlowControlRequest.py
aliyunsdkft/request/v20180713/FtParamListRequest.py
aliyunsdkft/request/v20180713/TestFlowStrategy01Request.py
aliyunsdkft/request/v20180713/TestHttpApiRequest.py
aliyunsdkft/request/v20180713/__init__.py
aliyun_python_sdk_ft-3.2.33.dist-info/LICENSE
aliyun_python_sdk_ft-3.2.33.dist-info/METADATA
aliyun_python_sdk_ft-3.2.33.dist-info/WHEEL
aliyun_python_sdk_ft-3.2.33.dist-info/top_level.txt
aliyun_python_sdk_ft-3.2.33.dist-info/RECORD
